gaico/__init__.py
gaico/experiment.py
gaico/thresholds.py
gaico/utils.py
gaico/visualize.py
gaico/metrics/__init__.py
gaico/metrics/base.py
gaico/metrics/ngram_metrics.py
gaico/metrics/semantic_similarity_metrics.py
gaico/metrics/text_similarity_metrics.py
gaico/metrics/textual.py
gaico/metrics/audio/__init__.py
gaico/metrics/audio/audio.py
gaico/metrics/image/__init__.py
gaico/metrics/image/image.py
gaico/metrics/structured/__init__.py
gaico/metrics/structured/structured.py
gaico-0.3.0.dist-info/METADATA
gaico-0.3.0.dist-info/WHEEL
gaico-0.3.0.dist-info/licenses/LICENSE
gaico-0.3.0.dist-info/RECORD
