Metadata-Version: 2.4
Name: GAICo
Version: 0.3.0
Summary: GenAI Results Comparator, GAICo, is a Python library to help compare, analyze and visualize outputs from Large Language Models (LLMs), often against a reference text. In doing so, one can use a range of extensible metrics from the literature.
Project-URL: Bug Tracker, https://github.com/ai4society/GenAIResultsComparator/issues
Project-URL: Documentation, https://ai4society.github.io/projects/GenAIResultsComparator/index.html
Project-URL: Homepage, https://github.com/ai4society/GenAIResultsComparator
Project-URL: Repository, https://github.com/ai4society/GenAIResultsComparator
Author-email: AI4Society Team <ai4societyteam@gmail.com>, Nitin Gupta <nitin1209@gmail.com>, Pallav Koppisetti <pallav.koppisetti5@gmail.com>, Kausik Lakkaraju <klakkaraju98@gmail.com>, Biplav Srivastava <prof.biplav@gmail.com>
Maintainer-email: AI4Society Team <ai4societyteam@gmail.com>, Nitin Gupta <nitin1209@gmail.com>
License: MIT License
License-File: LICENSE
Keywords: evaluation,generative-ai,llm,metrics,nlp,text-comparison
Classifier: Intended Audience :: Developers
Classifier: Intended Audience :: Science/Research
Classifier: License :: OSI Approved :: MIT License
Classifier: Operating System :: OS Independent
Classifier: Programming Language :: Python :: 3
Classifier: Programming Language :: Python :: 3.10
Classifier: Programming Language :: Python :: 3.11
Classifier: Programming Language :: Python :: 3.12
Classifier: Topic :: Scientific/Engineering :: Artificial Intelligence
Classifier: Topic :: Text Processing :: Linguistic
Requires-Python: <3.13,>=3.10
Requires-Dist: dtaidistance>=2.3.13
Requires-Dist: levenshtein>=0.23.0
Requires-Dist: matplotlib>=3.7.5
Requires-Dist: numpy>=1.26
Requires-Dist: pandas>=2.2.1
Requires-Dist: rouge-score>=0.1.2
Requires-Dist: seaborn>=0.13.0
Provides-Extra: audio
Requires-Dist: scipy>=1.15.3; extra == 'audio'
Requires-Dist: soundfile>=0.12.0; extra == 'audio'
Provides-Extra: bertscore
Requires-Dist: bert-score>=0.3.13; extra == 'bertscore'
Provides-Extra: cosine
Requires-Dist: scikit-learn==1.5.0; extra == 'cosine'
Provides-Extra: jsd
Requires-Dist: nltk>=3.9.1; extra == 'jsd'
Requires-Dist: scipy>=1.15.3; extra == 'jsd'
